{
    "schema":  1,
    "generatedAt":  "2026-05-23T20:00:04.2579083Z",
    "channel":  "stable",
    "source":  {
                   "kind":  "github-releases",
                   "owner":  "Reliquary-Tools",
                   "repo":  "releases",
                   "branch":  "main",
                   "manifestUrl":  "https://raw.githubusercontent.com/Reliquary-Tools/releases/main/manifest/stable.json"
               },
    "baseUrl":  "https://github.com/Reliquary-Tools/releases/releases/download",
    "apps":  {
                 "obelisk":  {
                                 "name":  "Obelisk",
                                 "latest":  "0.1.2",
                                 "description":  "RELIQUARY command center, updater and license hub.",
                                 "releaseTag":  "obelisk-v0.1.2",
                                 "windows-x64":  {
                                                     "url":  "https://github.com/Reliquary-Tools/releases/releases/download/obelisk-v0.1.2/Obelisk_0.1.2_x64_en-US.msi",
                                                     "file":  "Obelisk_0.1.2_x64_en-US.msi",
                                                     "sha256":  "0c0a23daa8e52bfb3313bf8454d22de14ec58d4486db26647b114ea957c16b28",
                                                     "size":  4939776
                                                 }
                             },
                 "daedalus":  {
                                  "name":  "Daedalus",
                                  "latest":  "0.1.0",
                                  "description":  "Video, playlist and audio acquisition.",
                                  "releaseTag":  "daedalus-v0.1.0",
                                  "windows-x64":  {
                                                      "url":  "https://github.com/Reliquary-Tools/releases/releases/download/daedalus-v0.1.0/Daedalus_0.1.0_x64_en-US.msi",
                                                      "file":  "Daedalus_0.1.0_x64_en-US.msi",
                                                      "sha256":  "3cafd82517197fd08ed12d97b6f48a985e787ccad152706e4b4ead48671532d6",
                                                      "size":  4460544
                                                  }
                              },
                 "chronos":  {
                                 "name":  "Chronos",
                                 "latest":  "0.1.0",
                                 "description":  "Frame timing normalization for video files.",
                                 "releaseTag":  "chronos-v0.1.0",
                                 "windows-x64":  {
                                                     "url":  "https://github.com/Reliquary-Tools/releases/releases/download/chronos-v0.1.0/Chronos_0.1.0_x64_en-US.msi",
                                                     "file":  "Chronos_0.1.0_x64_en-US.msi",
                                                     "sha256":  "4acd8384f0efd0251e828a21a35c4c3a153a61180512ec601e20c42d08c6325f",
                                                     "size":  4444160
                                                 }
                             }
             },
    "toolchain":  {
                      "strategy":  "providers",
                      "sharedDir":  "RELIQUARY/toolchain/bin",
                      "providers":  {
                                        "ffmpeg":  "https://www.gyan.dev/ffmpeg/builds/ffmpeg-release-essentials.zip",
                                        "ytDlp":  "https://github.com/yt-dlp/yt-dlp/releases/latest/download/yt-dlp.exe",
                                        "deno":  "https://github.com/denoland/deno/releases/latest/download/deno-x86_64-pc-windows-msvc.zip"
                                    }
                  }
}